python_eyes/__init__.py
python_eyes/python_eyes.py
tests/__init__.py
tests/test_create_instance.py
python_eyes-0.0.3.dist-info/LICENSE.txt
python_eyes-0.0.3.dist-info/METADATA
python_eyes-0.0.3.dist-info/WHEEL
python_eyes-0.0.3.dist-info/top_level.txt
python_eyes-0.0.3.dist-info/RECORD
