Metadata-Version: 2.1
Name: python-eyes
Version: 0.0.3
Summary: A package for Automation that compare two images and return if there is a difference between them
Home-page: https://github.com/den-iaremenko/python_eye
Author: Denys Iaremenko
Author-email: denysiaremenko@gmail.com
License: MIT
Project-URL: Documentation, https://github.com/den-iaremenko/python_eye
Project-URL: Funding, https://github.com/den-iaremenko/python_eye
Project-URL: Say Thanks!, https://github.com/den-iaremenko/python_eye
Project-URL: Source, https://github.com/den-iaremenko/python_eye
Project-URL: Tracker, https://github.com/den-iaremenko/python_eye/issues
Keywords: image difference,image comparisonappium,selenium,automation,ui validation
Platform: UNKNOWN
Classifier: Development Status :: 4 - Beta
Classifier: Programming Language :: Python
Classifier: Programming Language :: Python :: 3.7
Classifier: Programming Language :: Python :: 3.8
Classifier: Environment :: Console
Classifier: Environment :: MacOS X
Classifier: Intended Audience :: Developers
Classifier: Intended Audience :: Other Audience
Classifier: License :: OSI Approved :: MIT License
Classifier: Operating System :: OS Independent
Classifier: Topic :: Software Development :: Quality Assurance
Classifier: Topic :: Software Development :: Testing
Requires-Python: >=3.6
Requires-Dist: opencv-python (>=4.2.0.34)
Requires-Dist: loguru (>=0.4.1)
